__init__.py
pybump.py
pybump_patch.py
pybump_version.py
pybump-1.13.2.dist-info/licenses/LICENSE
pybump-1.13.2.dist-info/METADATA
pybump-1.13.2.dist-info/WHEEL
pybump-1.13.2.dist-info/entry_points.txt
pybump-1.13.2.dist-info/top_level.txt
pybump-1.13.2.dist-info/RECORD
