Metadata-Version: 2.4
Name: pybump
Version: 1.13.2
Summary: Python version bumper
Author-email: Arie Lev <levinsonarie@gmail.com>
Maintainer-email: Arie Lev <levinsonarie@gmail.com>
Keywords: bump,version,appVersion,versioning,helm,charts,pyproject.toml,setup.py,promote
Classifier: Programming Language :: Python :: 3
Classifier: Programming Language :: Python :: 3.8
Classifier: Programming Language :: Python :: 3.9
Classifier: Programming Language :: Python :: 3.10
Classifier: Programming Language :: Python :: 3.11
Classifier: Programming Language :: Python :: 3.12
Classifier: Programming Language :: Python :: 3.13
Classifier: Operating System :: OS Independent
License-File: LICENSE
Requires-Dist: packaging==24.2
Requires-Dist: ruamel.yaml==0.17.21
Requires-Dist: GitPython==3.1.41
Dynamic: license-file
